PayHero/__init__.py
PayHero/main.py
tests/__init__.py
tests/test_api.py
py_payhero-0.0.2.dist-info/LICENSE
py_payhero-0.0.2.dist-info/METADATA
py_payhero-0.0.2.dist-info/WHEEL
py_payhero-0.0.2.dist-info/top_level.txt
py_payhero-0.0.2.dist-info/RECORD
