Metadata-Version: 2.2
Name: py-payhero
Version: 0.0.2
Summary: A Python SDK for interacting with the PayHero API
Home-page: https://github.com/njeru-codes/PayHero-API-SDK-
Author: Njeru Mtwaiti
Author-email: newerbandit@proton.me
License: MIT
Classifier: Programming Language :: Python :: 3
Classifier: License :: OSI Approved :: MIT License
Classifier: Operating System :: OS Independent
Requires-Python: >=3.6
License-File: LICENSE
Requires-Dist: requests
Dynamic: author
Dynamic: author-email
Dynamic: classifier
Dynamic: description
Dynamic: description-content-type
Dynamic: home-page
Dynamic: license
Dynamic: requires-dist
Dynamic: requires-python
Dynamic: summary
